{
  "os":  "Linux-6.8.0-52-generic-x86_64-with-glibc2.35",
  "python":  "CPython 3.10.16",
  "startedAt":  "2025-02-25T11:21:17.965453Z",
  "program":  "/home/baris/repos/pipeline-grpo/nbs/grpo-trl.ipynb",
  "codePath":  "nbs/grpo-trl.ipynb",
  "git":  {
    "remote":  "git@github.com:bdsaglam/pipeline-grpo.git",
    "commit":  "5799a74ef536247b195f17d703827ef324742562"
  },
  "email":  "bdsaglam@gmail.com",
  "root":  "/home/baris/repos/pipeline-grpo/nbs",
  "host":  "amax7-desktop",
  "executable":  "/home/baris/miniconda3/envs/grpo/bin/python",
  "codePathLocal":  "grpo-trl.ipynb",
  "cpu_count":  64,
  "cpu_count_logical":  128,
  "gpu":  "NVIDIA A100 80GB PCIe",
  "gpu_count":  4,
  "disk":  {
    "/":  {
      "total":  "3778773131264",
      "used":  "1391796686848"
    }
  },
  "memory":  {
    "total":  "540657614848"
  },
  "cpu":  {
    "count":  64,
    "countLogical":  128
  },
  "gpu_nvidia":  [
    {
      "name":  "NVIDIA A100 80GB PCIe",
      "memoryTotal":  "85899345920",
      "cudaCores":  6912,
      "architecture":  "Ampere"
    },
    {
      "name":  "NVIDIA A100 80GB PCIe",
      "memoryTotal":  "85899345920",
      "cudaCores":  6912,
      "architecture":  "Ampere"
    },
    {
      "name":  "NVIDIA A100 80GB PCIe",
      "memoryTotal":  "85899345920",
      "cudaCores":  6912,
      "architecture":  "Ampere"
    },
    {
      "name":  "NVIDIA A100 80GB PCIe",
      "memoryTotal":  "85899345920",
      "cudaCores":  6912,
      "architecture":  "Ampere"
    }
  ],
  "cudaVersion":  "12.2"
}